xnemogcm/__init__.py
xnemogcm/arakawa_points.py
xnemogcm/domcfg.py
xnemogcm/merge.py
xnemogcm/metrics.py
xnemogcm/namelist.py
xnemogcm/nemo.py
xnemogcm/test/conftest.py
xnemogcm/test/test_dask.py
xnemogcm/test/test_domcfg.py
xnemogcm/test/test_merge.py
xnemogcm/test/test_metrics.py
xnemogcm/test/test_namelist.py
xnemogcm/test/test_nemo.py
xnemogcm/test/test_surface.py
xnemogcm/test/test_version.py
xnemogcm/tools.py
xnemogcm-0.5.0.post1.dist-info/LICENSE
xnemogcm-0.5.0.post1.dist-info/METADATA
xnemogcm-0.5.0.post1.dist-info/WHEEL
xnemogcm-0.5.0.post1.dist-info/RECORD
