Metadata-Version: 2.3
Name: xnemogcm
Version: 0.5.0.post1
Summary: Interface to open NEMO global circulation model output dataset and create a xgcm grid.
License: MIT
Author: Romain Caneill
Author-email: romain.caneill@ens-lyon.org
Requires-Python: >=3.9
Classifier: License :: OSI Approved :: MIT License
Classifier: Programming Language :: Python :: 3
Classifier: Programming Language :: Python :: 3.9
Classifier: Programming Language :: Python :: 3.10
Classifier: Programming Language :: Python :: 3.11
Classifier: Programming Language :: Python :: 3.12
Classifier: Programming Language :: Python :: 3.13
Provides-Extra: metrics
Provides-Extra: namelist
Requires-Dist: dask[array] (>=2022.01.0)
Requires-Dist: f90nml (>=1.3.1) ; extra == "namelist"
Requires-Dist: netcdf4 (>=1.5.8)
Requires-Dist: xarray (>=0.21.1)
Requires-Dist: xgcm (>=0.6.0) ; extra == "metrics"
Project-URL: Homepage, https://github.com/rcaneill/xnemogcm
